{"data":{"course_id":37,"stage":[{"id":71,"stage_name":"第一阶段","stage_image":"ch2_stage.png","stage_path":[{"file_name":"normal-unpass.png","file_name_pass":"normal-pass.png","x":578,"y":7234,"width":236,"height":221,"level":1,"text":"1"},{"file_name":"normal-unpass.png","file_name_pass":"normal-pass.png","x":616,"y":6872,"width":236,"height":221,"level":2,"text":"2"},{"file_name":"normal-unpass.png","file_name_pass":"normal-pass.png","x":564,"y":6541,"width":236,"height":221,"level":3,"text":"3"},{"file_name":"normal-unpass.png","file_name_pass":"normal-pass.png","x":420,"y":6219,"width":236,"height":221,"level":4,"text":"4"},{"file_name":"normal-unpass.png","file_name_pass":"normal-pass.png","x":331,"y":5881,"width":236,"height":221,"level":5,"text":"5"},{"file_name":"normal-unpass.png","file_name_pass":"normal-pass.png","x":339,"y":5523,"width":236,"height":221,"level":6,"text":"6"},{"file_name":"normal-unpass.png","file_name_pass":"normal-pass.png","x":450,"y":5181,"width":236,"height":221,"level":7,"text":"7"},{"file_name":"normal-unpass.png","file_name_pass":"normal-pass.png","x":578,"y":4829,"width":236,"height":221,"level":8,"text":"8"},{"file_name":"normal-unpass.png","file_name_pass":"normal-pass.png","x":595,"y":4434,"width":236,"height":221,"level":9,"text":"9"},{"file_name":"normal-unpass.png","file_name_pass":"normal-pass.png","x":488,"y":4024,"width":236,"height":221,"level":10,"text":"10"},{"file_name":"normal-unpass.png","file_name_pass":"normal-pass.png","x":317,"y":3621,"width":236,"height":221,"level":11,"text":"11"},{"file_name":"normal-unpass.png","file_name_pass":"normal-pass.png","x":318,"y":3206,"width":236,"height":221,"level":12,"text":"12"},{"file_name":"normal-unpass.png","file_name_pass":"normal-pass.png","x":461,"y":2798,"width":236,"height":221,"level":13,"text":"13"},{"file_name":"normal-unpass.png","file_name_pass":"normal-pass.png","x":593,"y":2392,"width":236,"height":221,"level":14,"text":"14"},{"file_name":"normal-unpass.png","file_name_pass":"normal-pass.png","x":601,"y":2030,"width":236,"height":221,"level":15,"text":"15"},{"file_name":"normal-unpass.png","file_name_pass":"normal-pass.png","x":473,"y":1635,"width":236,"height":221,"level":16,"text":"16"},{"file_name":"normal-unpass.png","file_name_pass":"normal-pass.png","x":325,"y":1277,"width":236,"height":221,"level":17,"text":"17"},{"file_name":"normal-unpass.png","file_name_pass":"normal-pass.png","x":325,"y":874,"width":236,"height":221,"level":18,"text":"18"},{"file_name":"normal-unpass.png","file_name_pass":"normal-pass.png","x":448,"y":484,"width":236,"height":221,"level":19,"text":"19"}],"stage_mask_image":"ch_stage1_blur.png","days":[{"id":621,"stage_day":1,"title":"B6U3基础训练一","test_flag":0,"content":"","tasks":[{"id":1025,"task_name":"B6U3基础训练一","task_image":"jichuxunlian.png","task_type":6,"duration":0,"task_detail":[{"id":37238,"content_id":52491,"sort":0,"content_type":1,"score":2},{"id":37239,"content_id":52494,"sort":0,"content_type":1,"score":3},{"id":37240,"content_id":52497,"sort":0,"content_type":1,"score":3},{"id":37241,"content_id":52500,"sort":0,"content_type":1,"score":3},{"id":37242,"content_id":52502,"sort":0,"content_type":1,"score":3},{"id":37243,"content_id":52513,"sort":0,"content_type":1,"score":3},{"id":37244,"content_id":52515,"sort":0,"content_type":1,"score":3},{"id":37245,"content_id":52516,"sort":0,"content_type":1,"score":3},{"id":37246,"content_id":52517,"sort":0,"content_type":1,"score":3},{"id":37247,"content_id":52518,"sort":0,"content_type":1,"score":3},{"id":37248,"content_id":52519,"sort":0,"content_type":1,"score":3},{"id":37249,"content_id":52520,"sort":0,"content_type":1,"score":3},{"id":37250,"content_id":52521,"sort":0,"content_type":1,"score":3},{"id":37251,"content_id":52522,"sort":0,"content_type":1,"score":3},{"id":37252,"content_id":52523,"sort":0,"content_type":1,"score":3},{"id":37253,"content_id":52524,"sort":0,"content_type":1,"score":3},{"id":37254,"content_id":52525,"sort":0,"content_type":1,"score":3},{"id":37255,"content_id":52531,"sort":0,"content_type":1,"score":3},{"id":37256,"content_id":52535,"sort":0,"content_type":1,"score":3},{"id":37257,"content_id":52536,"sort":0,"content_type":1,"score":3},{"id":37258,"content_id":52538,"sort":0,"content_type":1,"score":3},{"id":37259,"content_id":52541,"sort":0,"content_type":1,"score":3},{"id":37260,"content_id":52544,"sort":0,"content_type":1,"score":3},{"id":37261,"content_id":52547,"sort":0,"content_type":1,"score":3},{"id":37262,"content_id":52550,"sort":0,"content_type":1,"score":3},{"id":37263,"content_id":52554,"sort":0,"content_type":1,"score":2},{"id":37264,"content_id":52556,"sort":0,"content_type":1,"score":2},{"id":37265,"content_id":52558,"sort":0,"content_type":1,"score":2},{"id":37266,"content_id":52559,"sort":0,"content_type":1,"score":2},{"id":37267,"content_id":52576,"sort":0,"content_type":1,"score":2},{"id":37268,"content_id":52578,"sort":0,"content_type":1,"score":2},{"id":37269,"content_id":52579,"sort":0,"content_type":1,"score":2},{"id":37270,"content_id":52582,"sort":0,"content_type":1,"score":4},{"id":37271,"content_id":52584,"sort":0,"content_type":1,"score":4},{"id":37272,"content_id":52585,"sort":0,"content_type":1,"score":4}]}]},{"id":622,"stage_day":2,"title":"B6U3基础训练二","test_flag":0,"content":"","tasks":[{"id":1121,"task_name":"B6U3基础训练二","task_image":"jichuxunlian.png","task_type":6,"duration":0,"task_detail":[{"id":38849,"content_id":52654,"sort":0,"content_type":1,"score":4},{"id":38850,"content_id":52655,"sort":0,"content_type":1,"score":4},{"id":38851,"content_id":52659,"sort":0,"content_type":1,"score":4},{"id":38852,"content_id":52660,"sort":0,"content_type":1,"score":4},{"id":38853,"content_id":52667,"sort":0,"content_type":1,"score":4},{"id":38854,"content_id":52670,"sort":0,"content_type":1,"score":4},{"id":38855,"content_id":52672,"sort":0,"content_type":1,"score":4},{"id":38857,"content_id":52677,"sort":0,"content_type":1,"score":4},{"id":38858,"content_id":52678,"sort":0,"content_type":1,"score":3},{"id":38859,"content_id":52679,"sort":0,"content_type":1,"score":3},{"id":38860,"content_id":52680,"sort":0,"content_type":1,"score":3},{"id":38861,"content_id":52681,"sort":0,"content_type":1,"score":3},{"id":38862,"content_id":52685,"sort":0,"content_type":1,"score":4},{"id":38863,"content_id":52686,"sort":0,"content_type":1,"score":4},{"id":38864,"content_id":52687,"sort":0,"content_type":1,"score":4},{"id":38865,"content_id":52688,"sort":0,"content_type":1,"score":5},{"id":38866,"content_id":52689,"sort":0,"content_type":1,"score":5},{"id":38867,"content_id":52690,"sort":0,"content_type":1,"score":5},{"id":38868,"content_id":52691,"sort":0,"content_type":1,"score":5},{"id":38869,"content_id":52731,"sort":0,"content_type":1,"score":8},{"id":38870,"content_id":52735,"sort":0,"content_type":1,"score":8},{"id":38871,"content_id":52738,"sort":0,"content_type":1,"score":8}]}]},{"id":623,"stage_day":3,"title":"B6U3综合提高","test_flag":0,"content":"","tasks":[{"id":1122,"task_name":"B6U3综合提高","task_image":"jichuxunlian.png","task_type":6,"duration":0,"task_detail":[{"id":38908,"content_id":52860,"sort":0,"content_type":1,"score":2},{"id":38909,"content_id":52861,"sort":0,"content_type":1,"score":2},{"id":38910,"content_id":52862,"sort":0,"content_type":1,"score":2},{"id":38911,"content_id":52863,"sort":0,"content_type":1,"score":2},{"id":38912,"content_id":52864,"sort":0,"content_type":1,"score":2},{"id":38913,"content_id":52865,"sort":0,"content_type":1,"score":2},{"id":38914,"content_id":52867,"sort":0,"content_type":1,"score":2},{"id":38915,"content_id":52868,"sort":0,"content_type":1,"score":2},{"id":38916,"content_id":52871,"sort":0,"content_type":1,"score":2},{"id":38917,"content_id":52875,"sort":0,"content_type":1,"score":2},{"id":38918,"content_id":52879,"sort":0,"content_type":1,"score":2},{"id":38919,"content_id":52886,"sort":0,"content_type":1,"score":2},{"id":38920,"content_id":52891,"sort":0,"content_type":1,"score":2},{"id":38921,"content_id":52893,"sort":0,"content_type":1,"score":2},{"id":38922,"content_id":52894,"sort":0,"content_type":1,"score":2},{"id":38923,"content_id":52902,"sort":0,"content_type":1,"score":2},{"id":38924,"content_id":52907,"sort":0,"content_type":1,"score":2},{"id":38925,"content_id":52909,"sort":0,"content_type":1,"score":2},{"id":38926,"content_id":52914,"sort":0,"content_type":1,"score":3},{"id":38927,"content_id":52915,"sort":0,"content_type":1,"score":3},{"id":38928,"content_id":52916,"sort":0,"content_type":1,"score":3},{"id":38929,"content_id":52917,"sort":0,"content_type":1,"score":3},{"id":38930,"content_id":52944,"sort":0,"content_type":1,"score":3},{"id":38931,"content_id":52945,"sort":0,"content_type":1,"score":3},{"id":38932,"content_id":52946,"sort":0,"content_type":1,"score":3},{"id":38933,"content_id":52949,"sort":0,"content_type":1,"score":3},{"id":38934,"content_id":52955,"sort":0,"content_type":1,"score":3},{"id":38935,"content_id":52957,"sort":0,"content_type":1,"score":2},{"id":38936,"content_id":52972,"sort":0,"content_type":1,"score":2},{"id":38937,"content_id":52975,"sort":0,"content_type":1,"score":2},{"id":38938,"content_id":52977,"sort":0,"content_type":1,"score":2},{"id":38939,"content_id":52978,"sort":0,"content_type":1,"score":2},{"id":38940,"content_id":52979,"sort":0,"content_type":1,"score":2},{"id":38941,"content_id":52980,"sort":0,"content_type":1,"score":5},{"id":38942,"content_id":52982,"sort":0,"content_type":1,"score":5},{"id":38943,"content_id":52985,"sort":0,"content_type":1,"score":5},{"id":38944,"content_id":52989,"sort":0,"content_type":1,"score":5},{"id":38945,"content_id":52994,"sort":0,"content_type":1,"score":5}]}]},{"id":624,"stage_day":4,"title":"B6U4基础训练一","test_flag":0,"content":"","tasks":[{"id":1123,"task_name":"B6U4基础训练一","task_image":"jichuxunlian.png","task_type":6,"duration":0,"task_detail":[{"id":39027,"content_id":53112,"sort":0,"content_type":1,"score":3},{"id":39028,"content_id":53118,"sort":0,"content_type":1,"score":3},{"id":39029,"content_id":53122,"sort":0,"content_type":1,"score":3},{"id":39030,"content_id":53124,"sort":0,"content_type":1,"score":3},{"id":39031,"content_id":53144,"sort":0,"content_type":1,"score":3},{"id":39032,"content_id":53151,"sort":0,"content_type":1,"score":3},{"id":39033,"content_id":53153,"sort":0,"content_type":1,"score":3},{"id":39034,"content_id":53155,"sort":0,"content_type":1,"score":3},{"id":39035,"content_id":53157,"sort":0,"content_type":1,"score":3},{"id":39036,"content_id":53159,"sort":0,"content_type":1,"score":3},{"id":39037,"content_id":53160,"sort":0,"content_type":1,"score":3},{"id":39038,"content_id":53207,"sort":0,"content_type":1,"score":3},{"id":39039,"content_id":53208,"sort":0,"content_type":1,"score":3},{"id":39040,"content_id":53209,"sort":0,"content_type":1,"score":3},{"id":39047,"content_id":53212,"sort":0,"content_type":1,"score":3},{"id":39048,"content_id":53215,"sort":0,"content_type":1,"score":3},{"id":39049,"content_id":53217,"sort":0,"content_type":1,"score":3},{"id":39050,"content_id":53220,"sort":0,"content_type":1,"score":3},{"id":39051,"content_id":53227,"sort":0,"content_type":1,"score":2},{"id":39052,"content_id":53230,"sort":0,"content_type":1,"score":2},{"id":39053,"content_id":53236,"sort":0,"content_type":1,"score":2},{"id":39054,"content_id":53239,"sort":0,"content_type":1,"score":3},{"id":39055,"content_id":53243,"sort":0,"content_type":1,"score":3},{"id":39056,"content_id":53245,"sort":0,"content_type":1,"score":3},{"id":39057,"content_id":53247,"sort":0,"content_type":1,"score":3},{"id":39058,"content_id":53248,"sort":0,"content_type":1,"score":3},{"id":39059,"content_id":53250,"sort":0,"content_type":1,"score":3},{"id":39060,"content_id":53252,"sort":0,"content_type":1,"score":3},{"id":39061,"content_id":53253,"sort":0,"content_type":1,"score":3},{"id":39062,"content_id":53255,"sort":0,"content_type":1,"score":4},{"id":39063,"content_id":53256,"sort":0,"content_type":1,"score":4},{"id":39064,"content_id":53259,"sort":0,"content_type":1,"score":4},{"id":39065,"content_id":53261,"sort":0,"content_type":1,"score":4}]}]},{"id":625,"stage_day":5,"title":"B6U4基础训练二","test_flag":0,"content":"","tasks":[{"id":1124,"task_name":"B6U4基础训练二","task_image":"jichuxunlian.png","task_type":6,"duration":0,"task_detail":[{"id":39066,"content_id":53262,"sort":1,"content_type":1,"score":2},{"id":39067,"content_id":53264,"sort":2,"content_type":1,"score":3},{"id":39068,"content_id":53265,"sort":3,"content_type":1,"score":3},{"id":39069,"content_id":53267,"sort":4,"content_type":1,"score":3},{"id":39070,"content_id":53270,"sort":5,"content_type":1,"score":3},{"id":39071,"content_id":53275,"sort":6,"content_type":1,"score":3},{"id":39072,"content_id":53287,"sort":7,"content_type":1,"score":3},{"id":39073,"content_id":53288,"sort":8,"content_type":1,"score":3},{"id":39074,"content_id":53291,"sort":9,"content_type":1,"score":3},{"id":39075,"content_id":53294,"sort":10,"content_type":1,"score":3},{"id":39076,"content_id":53297,"sort":11,"content_type":1,"score":3},{"id":39077,"content_id":53298,"sort":12,"content_type":1,"score":3},{"id":39078,"content_id":53301,"sort":13,"content_type":1,"score":3},{"id":39198,"content_id":53302,"sort":14,"content_type":1,"score":2},{"id":39079,"content_id":53303,"sort":15,"content_type":1,"score":3},{"id":39080,"content_id":53304,"sort":16,"content_type":1,"score":3},{"id":39081,"content_id":53306,"sort":17,"content_type":1,"score":3},{"id":39082,"content_id":53305,"sort":18,"content_type":1,"score":3},{"id":39083,"content_id":53310,"sort":19,"content_type":1,"score":3},{"id":39084,"content_id":53313,"sort":20,"content_type":1,"score":3},{"id":39085,"content_id":53314,"sort":21,"content_type":1,"score":3},{"id":39086,"content_id":53317,"sort":22,"content_type":1,"score":3},{"id":39087,"content_id":53318,"sort":23,"content_type":1,"score":3},{"id":39088,"content_id":53319,"sort":24,"content_type":1,"score":3},{"id":39089,"content_id":53320,"sort":25,"content_type":1,"score":3},{"id":39090,"content_id":53321,"sort":26,"content_type":1,"score":3},{"id":39091,"content_id":53322,"sort":27,"content_type":1,"score":3},{"id":39092,"content_id":53323,"sort":28,"content_type":1,"score":3},{"id":39093,"content_id":53324,"sort":29,"content_type":1,"score":3},{"id":39094,"content_id":53325,"sort":30,"content_type":1,"score":5},{"id":39095,"content_id":53328,"sort":31,"content_type":1,"score":5},{"id":39096,"content_id":53331,"sort":32,"content_type":1,"score":5}]}]},{"id":626,"stage_day":6,"title":"B6U4综合提高","test_flag":0,"content":"","tasks":[{"id":1125,"task_name":"B6U4综合提高","task_image":"jichuxunlian.png","task_type":6,"duration":0,"task_detail":[{"id":39097,"content_id":53334,"sort":1,"content_type":1,"score":2},{"id":39098,"content_id":53336,"sort":2,"content_type":1,"score":2},{"id":39099,"content_id":53338,"sort":3,"content_type":1,"score":2},{"id":39100,"content_id":53339,"sort":4,"content_type":1,"score":2},{"id":39101,"content_id":53340,"sort":5,"content_type":1,"score":2},{"id":39102,"content_id":53342,"sort":6,"content_type":1,"score":2},{"id":39103,"content_id":53345,"sort":7,"content_type":1,"score":2},{"id":39104,"content_id":53349,"sort":8,"content_type":1,"score":2},{"id":39105,"content_id":53351,"sort":9,"content_type":1,"score":3},{"id":39106,"content_id":53352,"sort":10,"content_type":1,"score":3},{"id":39107,"content_id":53353,"sort":11,"content_type":1,"score":3},{"id":39108,"content_id":53354,"sort":12,"content_type":1,"score":3},{"id":39109,"content_id":53355,"sort":13,"content_type":1,"score":3},{"id":39110,"content_id":53356,"sort":14,"content_type":1,"score":3},{"id":39111,"content_id":53363,"sort":15,"content_type":1,"score":3},{"id":39112,"content_id":53364,"sort":16,"content_type":1,"score":3},{"id":39113,"content_id":53365,"sort":17,"content_type":1,"score":3},{"id":39479,"content_id":53378,"sort":18,"content_type":1,"score":2},{"id":39480,"content_id":53379,"sort":19,"content_type":1,"score":2},{"id":39481,"content_id":53380,"sort":20,"content_type":1,"score":2},{"id":39482,"content_id":53381,"sort":21,"content_type":1,"score":2},{"id":39115,"content_id":53367,"sort":22,"content_type":1,"score":3},{"id":39116,"content_id":53368,"sort":23,"content_type":1,"score":3},{"id":39117,"content_id":53369,"sort":24,"content_type":1,"score":3},{"id":39118,"content_id":53370,"sort":25,"content_type":1,"score":2},{"id":39119,"content_id":53371,"sort":26,"content_type":1,"score":2},{"id":39120,"content_id":53372,"sort":27,"content_type":1,"score":2},{"id":39121,"content_id":53373,"sort":28,"content_type":1,"score":2},{"id":39122,"content_id":53374,"sort":29,"content_type":1,"score":2},{"id":39123,"content_id":53375,"sort":30,"content_type":1,"score":2},{"id":39124,"content_id":53376,"sort":31,"content_type":1,"score":2},{"id":39125,"content_id":53377,"sort":32,"content_type":1,"score":2},{"id":39126,"content_id":53393,"sort":33,"content_type":1,"score":4},{"id":39127,"content_id":53394,"sort":34,"content_type":1,"score":4},{"id":39128,"content_id":53395,"sort":35,"content_type":1,"score":4},{"id":39129,"content_id":53396,"sort":36,"content_type":1,"score":4},{"id":39130,"content_id":53399,"sort":37,"content_type":1,"score":4},{"id":39131,"content_id":53403,"sort":38,"content_type":1,"score":4}]}]},{"id":627,"stage_day":7,"title":"B6U5基础训练一","test_flag":0,"content":"","tasks":[{"id":1126,"task_name":"B6U5基础训练一","task_image":"jichuxunlian.png","task_type":6,"duration":0,"task_detail":[{"id":39132,"content_id":53407,"sort":0,"content_type":1,"score":3},{"id":39133,"content_id":53410,"sort":0,"content_type":1,"score":3},{"id":39134,"content_id":53413,"sort":0,"content_type":1,"score":3},{"id":39135,"content_id":53419,"sort":0,"content_type":1,"score":3},{"id":39136,"content_id":53421,"sort":0,"content_type":1,"score":3},{"id":39137,"content_id":53423,"sort":0,"content_type":1,"score":3},{"id":39138,"content_id":53425,"sort":0,"content_type":1,"score":3},{"id":39139,"content_id":53427,"sort":0,"content_type":1,"score":3},{"id":39140,"content_id":53429,"sort":0,"content_type":1,"score":3},{"id":39141,"content_id":53432,"sort":0,"content_type":1,"score":3},{"id":39142,"content_id":53433,"sort":0,"content_type":1,"score":4},{"id":39143,"content_id":53435,"sort":0,"content_type":1,"score":4},{"id":39144,"content_id":53437,"sort":0,"content_type":1,"score":4},{"id":39145,"content_id":53438,"sort":0,"content_type":1,"score":4},{"id":39146,"content_id":53439,"sort":0,"content_type":1,"score":4},{"id":39147,"content_id":53441,"sort":0,"content_type":1,"score":4},{"id":39148,"content_id":53443,"sort":0,"content_type":1,"score":4},{"id":39149,"content_id":53444,"sort":0,"content_type":1,"score":4},{"id":39150,"content_id":53445,"sort":0,"content_type":1,"score":4},{"id":39151,"content_id":53447,"sort":0,"content_type":1,"score":4},{"id":39152,"content_id":53449,"sort":0,"content_type":1,"score":3},{"id":39153,"content_id":53451,"sort":0,"content_type":1,"score":3},{"id":39154,"content_id":53452,"sort":0,"content_type":1,"score":3},{"id":39155,"content_id":53454,"sort":0,"content_type":1,"score":3},{"id":39156,"content_id":53456,"sort":0,"content_type":1,"score":3},{"id":39157,"content_id":53457,"sort":0,"content_type":1,"score":3},{"id":39158,"content_id":53458,"sort":0,"content_type":1,"score":6},{"id":39159,"content_id":53459,"sort":0,"content_type":1,"score":6}]}]},{"id":688,"stage_day":8,"title":"B6U5基础训练二","test_flag":0,"content":"","tasks":[{"id":1130,"task_name":"B6U5基础训练二","task_image":"jichuxunlian.png","task_type":6,"duration":0,"task_detail":[{"id":39165,"content_id":53460,"sort":0,"content_type":1,"score":2},{"id":39166,"content_id":53461,"sort":0,"content_type":1,"score":2},{"id":39167,"content_id":53462,"sort":0,"content_type":1,"score":2},{"id":39168,"content_id":53463,"sort":0,"content_type":1,"score":2},{"id":39169,"content_id":53465,"sort":0,"content_type":1,"score":2},{"id":39170,"content_id":53467,"sort":0,"content_type":1,"score":2},{"id":39171,"content_id":53469,"sort":0,"content_type":1,"score":2},{"id":39172,"content_id":53473,"sort":0,"content_type":1,"score":2},{"id":39173,"content_id":53474,"sort":0,"content_type":1,"score":3},{"id":39174,"content_id":53475,"sort":0,"content_type":1,"score":3},{"id":39175,"content_id":53476,"sort":0,"content_type":1,"score":3},{"id":39176,"content_id":53479,"sort":0,"content_type":1,"score":3},{"id":39177,"content_id":53481,"sort":0,"content_type":1,"score":3},{"id":39178,"content_id":53483,"sort":0,"content_type":1,"score":3},{"id":39179,"content_id":53484,"sort":0,"content_type":1,"score":3},{"id":39180,"content_id":53485,"sort":0,"content_type":1,"score":3},{"id":39181,"content_id":53486,"sort":0,"content_type":1,"score":3},{"id":39182,"content_id":53487,"sort":0,"content_type":1,"score":3},{"id":39183,"content_id":53488,"sort":0,"content_type":1,"score":3},{"id":39184,"content_id":53489,"sort":0,"content_type":1,"score":3},{"id":39185,"content_id":53490,"sort":0,"content_type":1,"score":3},{"id":39186,"content_id":53491,"sort":0,"content_type":1,"score":3},{"id":39187,"content_id":53492,"sort":0,"content_type":1,"score":3},{"id":39188,"content_id":53477,"sort":0,"content_type":1,"score":3},{"id":39189,"content_id":53478,"sort":0,"content_type":1,"score":3},{"id":39190,"content_id":53480,"sort":0,"content_type":1,"score":3},{"id":39191,"content_id":53482,"sort":0,"content_type":1,"score":3},{"id":39192,"content_id":53470,"sort":0,"content_type":1,"score":3},{"id":39193,"content_id":53471,"sort":0,"content_type":1,"score":3},{"id":39194,"content_id":53472,"sort":0,"content_type":1,"score":3},{"id":39195,"content_id":53464,"sort":0,"content_type":1,"score":6},{"id":39196,"content_id":53466,"sort":0,"content_type":1,"score":6},{"id":39197,"content_id":53468,"sort":0,"content_type":1,"score":6}]}]},{"id":689,"stage_day":9,"title":"B6U5综合提高","test_flag":0,"content":"","tasks":[{"id":1104,"task_name":"B6U5综合提高","task_image":"jichuxunlian.png","task_type":6,"duration":0,"task_detail":[{"id":38512,"content_id":53397,"sort":0,"content_type":1,"score":2},{"id":38513,"content_id":53398,"sort":0,"content_type":1,"score":2},{"id":38514,"content_id":53400,"sort":0,"content_type":1,"score":2},{"id":38515,"content_id":53401,"sort":0,"content_type":1,"score":2},{"id":38516,"content_id":53402,"sort":0,"content_type":1,"score":2},{"id":38517,"content_id":53404,"sort":0,"content_type":1,"score":2},{"id":38518,"content_id":53405,"sort":0,"content_type":1,"score":3},{"id":38519,"content_id":53406,"sort":0,"content_type":1,"score":3},{"id":38520,"content_id":53408,"sort":0,"content_type":1,"score":3},{"id":38521,"content_id":53409,"sort":0,"content_type":1,"score":3},{"id":38522,"content_id":53411,"sort":0,"content_type":1,"score":3},{"id":38523,"content_id":53412,"sort":0,"content_type":1,"score":3},{"id":38524,"content_id":53414,"sort":0,"content_type":1,"score":3},{"id":38525,"content_id":53415,"sort":0,"content_type":1,"score":3},{"id":38526,"content_id":53416,"sort":0,"content_type":1,"score":3},{"id":38527,"content_id":53417,"sort":0,"content_type":1,"score":3},{"id":38528,"content_id":53418,"sort":0,"content_type":1,"score":3},{"id":38529,"content_id":53420,"sort":0,"content_type":1,"score":3},{"id":38530,"content_id":53422,"sort":0,"content_type":1,"score":3},{"id":38531,"content_id":53424,"sort":0,"content_type":1,"score":3},{"id":38532,"content_id":53426,"sort":0,"content_type":1,"score":3},{"id":38533,"content_id":53428,"sort":0,"content_type":1,"score":3},{"id":38534,"content_id":53430,"sort":0,"content_type":1,"score":3},{"id":38535,"content_id":53431,"sort":0,"content_type":1,"score":3},{"id":38536,"content_id":53434,"sort":0,"content_type":1,"score":3},{"id":38537,"content_id":53436,"sort":0,"content_type":1,"score":3},{"id":38538,"content_id":53440,"sort":0,"content_type":1,"score":4},{"id":38539,"content_id":53442,"sort":0,"content_type":1,"score":4},{"id":38554,"content_id":53446,"sort":0,"content_type":1,"score":4},{"id":38555,"content_id":53448,"sort":0,"content_type":1,"score":4},{"id":38556,"content_id":53450,"sort":0,"content_type":1,"score":4},{"id":38557,"content_id":53453,"sort":0,"content_type":1,"score":4},{"id":38558,"content_id":53455,"sort":0,"content_type":1,"score":4}]}]},{"id":690,"stage_day":10,"title":"B6跟踪检测","test_flag":0,"content":"","tasks":[{"id":1105,"task_name":"B6跟踪检测","task_image":"jichuxunlian.png","task_type":6,"duration":0,"task_detail":[{"id":38572,"content_id":52813,"sort":0,"content_type":1,"score":2},{"id":38573,"content_id":52815,"sort":0,"content_type":1,"score":2},{"id":38574,"content_id":52816,"sort":0,"content_type":1,"score":2},{"id":38575,"content_id":52818,"sort":0,"content_type":1,"score":2},{"id":38576,"content_id":52820,"sort":0,"content_type":1,"score":2},{"id":38577,"content_id":52823,"sort":0,"content_type":1,"score":2},{"id":38578,"content_id":52825,"sort":0,"content_type":1,"score":2},{"id":38579,"content_id":52827,"sort":0,"content_type":1,"score":2},{"id":38580,"content_id":52828,"sort":0,"content_type":1,"score":2},{"id":38581,"content_id":52830,"sort":0,"content_type":1,"score":2},{"id":38582,"content_id":52834,"sort":0,"content_type":1,"score":2},{"id":38583,"content_id":52835,"sort":0,"content_type":1,"score":2},{"id":38584,"content_id":52836,"sort":0,"content_type":1,"score":2},{"id":38585,"content_id":52843,"sort":0,"content_type":1,"score":2},{"id":38586,"content_id":52849,"sort":0,"content_type":1,"score":2},{"id":38587,"content_id":52850,"sort":0,"content_type":1,"score":2},{"id":38588,"content_id":52852,"sort":0,"content_type":1,"score":2},{"id":38589,"content_id":52854,"sort":0,"content_type":1,"score":2},{"id":38590,"content_id":52856,"sort":0,"content_type":1,"score":2},{"id":38591,"content_id":52858,"sort":0,"content_type":1,"score":2},{"id":38592,"content_id":52859,"sort":0,"content_type":1,"score":2},{"id":38593,"content_id":52866,"sort":0,"content_type":1,"score":2},{"id":38594,"content_id":52869,"sort":0,"content_type":1,"score":2},{"id":38595,"content_id":52870,"sort":0,"content_type":1,"score":2},{"id":38596,"content_id":52872,"sort":0,"content_type":1,"score":2},{"id":38597,"content_id":52873,"sort":0,"content_type":1,"score":2},{"id":38598,"content_id":52874,"sort":0,"content_type":1,"score":2},{"id":38599,"content_id":52876,"sort":0,"content_type":1,"score":2},{"id":38600,"content_id":52877,"sort":0,"content_type":1,"score":2},{"id":38601,"content_id":52878,"sort":0,"content_type":1,"score":2},{"id":38602,"content_id":52880,"sort":0,"content_type":1,"score":2},{"id":38603,"content_id":52881,"sort":0,"content_type":1,"score":2},{"id":38604,"content_id":52895,"sort":0,"content_type":1,"score":2},{"id":38605,"content_id":52896,"sort":0,"content_type":1,"score":2},{"id":38606,"content_id":52912,"sort":0,"content_type":1,"score":2},{"id":38607,"content_id":52913,"sort":0,"content_type":1,"score":2},{"id":38608,"content_id":52918,"sort":0,"content_type":1,"score":2},{"id":38609,"content_id":52919,"sort":0,"content_type":1,"score":2},{"id":38610,"content_id":52922,"sort":0,"content_type":1,"score":2},{"id":38611,"content_id":52924,"sort":0,"content_type":1,"score":2},{"id":38612,"content_id":52926,"sort":0,"content_type":1,"score":2},{"id":38613,"content_id":52927,"sort":0,"content_type":1,"score":2},{"id":38614,"content_id":52930,"sort":0,"content_type":1,"score":2},{"id":38615,"content_id":52932,"sort":0,"content_type":1,"score":2},{"id":38616,"content_id":52933,"sort":0,"content_type":1,"score":2},{"id":38617,"content_id":52935,"sort":0,"content_type":1,"score":2},{"id":38618,"content_id":52936,"sort":0,"content_type":1,"score":2},{"id":38619,"content_id":52937,"sort":0,"content_type":1,"score":2},{"id":38620,"content_id":52938,"sort":0,"content_type":1,"score":2},{"id":38621,"content_id":52939,"sort":0,"content_type":1,"score":2}]}]},{"id":691,"stage_day":11,"title":"B7U1基础训练一","test_flag":0,"content":"","tasks":[{"id":1106,"task_name":"B7U1基础训练一","task_image":"jichuxunlian.png","task_type":6,"duration":0,"task_detail":[{"id":38622,"content_id":52750,"sort":0,"content_type":1,"score":3},{"id":38623,"content_id":52751,"sort":0,"content_type":1,"score":3},{"id":38624,"content_id":52752,"sort":0,"content_type":1,"score":3},{"id":38625,"content_id":52753,"sort":0,"content_type":1,"score":3},{"id":38626,"content_id":52754,"sort":0,"content_type":1,"score":3},{"id":38627,"content_id":52757,"sort":0,"content_type":1,"score":3},{"id":38628,"content_id":52758,"sort":0,"content_type":1,"score":3},{"id":38629,"content_id":52759,"sort":0,"content_type":1,"score":3},{"id":38630,"content_id":52760,"sort":0,"content_type":1,"score":3},{"id":38631,"content_id":52761,"sort":0,"content_type":1,"score":3},{"id":38632,"content_id":52763,"sort":0,"content_type":1,"score":3},{"id":38633,"content_id":52765,"sort":0,"content_type":1,"score":3},{"id":38634,"content_id":52767,"sort":0,"content_type":1,"score":3},{"id":38635,"content_id":52769,"sort":0,"content_type":1,"score":3},{"id":38636,"content_id":52770,"sort":0,"content_type":1,"score":3},{"id":38637,"content_id":52772,"sort":0,"content_type":1,"score":3},{"id":38638,"content_id":52773,"sort":0,"content_type":1,"score":3},{"id":38639,"content_id":52775,"sort":0,"content_type":1,"score":3},{"id":38640,"content_id":52777,"sort":0,"content_type":1,"score":3},{"id":38641,"content_id":52778,"sort":0,"content_type":1,"score":3},{"id":38642,"content_id":52814,"sort":0,"content_type":1,"score":3},{"id":38643,"content_id":52817,"sort":0,"content_type":1,"score":3},{"id":38644,"content_id":52819,"sort":0,"content_type":1,"score":3},{"id":38645,"content_id":52821,"sort":0,"content_type":1,"score":3},{"id":38646,"content_id":52822,"sort":0,"content_type":1,"score":4},{"id":38647,"content_id":52824,"sort":0,"content_type":1,"score":4},{"id":38648,"content_id":52826,"sort":0,"content_type":1,"score":4},{"id":38649,"content_id":52829,"sort":0,"content_type":1,"score":4},{"id":38650,"content_id":52831,"sort":0,"content_type":1,"score":4},{"id":38651,"content_id":52832,"sort":0,"content_type":1,"score":4},{"id":38652,"content_id":52833,"sort":0,"content_type":1,"score":4}]}]},{"id":692,"stage_day":12,"title":"B7U1基础训练二","test_flag":0,"content":"","tasks":[{"id":1107,"task_name":"B7U1基础训练二","task_image":"jichuxunlian.png","task_type":6,"duration":0,"task_detail":[{"id":38667,"content_id":52837,"sort":0,"content_type":1,"score":3},{"id":38668,"content_id":52838,"sort":0,"content_type":1,"score":3},{"id":38669,"content_id":52839,"sort":0,"content_type":1,"score":3},{"id":38670,"content_id":52840,"sort":0,"content_type":1,"score":3},{"id":38671,"content_id":52841,"sort":0,"content_type":1,"score":3},{"id":38672,"content_id":52842,"sort":0,"content_type":1,"score":3},{"id":38673,"content_id":52844,"sort":0,"content_type":1,"score":3},{"id":38674,"content_id":52845,"sort":0,"content_type":1,"score":3},{"id":38675,"content_id":52846,"sort":0,"content_type":1,"score":3},{"id":38676,"content_id":52847,"sort":0,"content_type":1,"score":3},{"id":38677,"content_id":52848,"sort":0,"content_type":1,"score":3},{"id":38678,"content_id":52853,"sort":0,"content_type":1,"score":3},{"id":38679,"content_id":52851,"sort":0,"content_type":1,"score":3},{"id":38680,"content_id":52855,"sort":0,"content_type":1,"score":3},{"id":38695,"content_id":52857,"sort":0,"content_type":1,"score":3},{"id":38696,"content_id":52948,"sort":0,"content_type":1,"score":3},{"id":38697,"content_id":52951,"sort":0,"content_type":1,"score":3},{"id":38698,"content_id":52953,"sort":0,"content_type":1,"score":3},{"id":38699,"content_id":52960,"sort":0,"content_type":1,"score":3},{"id":38700,"content_id":52961,"sort":0,"content_type":1,"score":3},{"id":38701,"content_id":52962,"sort":0,"content_type":1,"score":3},{"id":38702,"content_id":52964,"sort":0,"content_type":1,"score":3},{"id":38703,"content_id":52965,"sort":0,"content_type":1,"score":3},{"id":38704,"content_id":52966,"sort":0,"content_type":1,"score":3},{"id":38705,"content_id":52967,"sort":0,"content_type":1,"score":3},{"id":38706,"content_id":52968,"sort":0,"content_type":1,"score":3},{"id":38707,"content_id":52969,"sort":0,"content_type":1,"score":3},{"id":38708,"content_id":52970,"sort":0,"content_type":1,"score":3},{"id":38709,"content_id":52971,"sort":0,"content_type":1,"score":4},{"id":38710,"content_id":52973,"sort":0,"content_type":1,"score":4},{"id":38711,"content_id":52974,"sort":0,"content_type":1,"score":4},{"id":38712,"content_id":52976,"sort":0,"content_type":1,"score":4}]}]},{"id":693,"stage_day":13,"title":"B7U1综合提高","test_flag":0,"content":"","tasks":[{"id":1108,"task_name":"B7U1综合提高","task_image":"jichuxunlian.png","task_type":6,"duration":0,"task_detail":[{"id":38726,"content_id":52986,"sort":0,"content_type":1,"score":2},{"id":38727,"content_id":52987,"sort":0,"content_type":1,"score":2},{"id":38728,"content_id":52990,"sort":0,"content_type":1,"score":2},{"id":38729,"content_id":52993,"sort":0,"content_type":1,"score":2},{"id":38730,"content_id":52995,"sort":0,"content_type":1,"score":2},{"id":38731,"content_id":52996,"sort":0,"content_type":1,"score":2},{"id":38732,"content_id":52997,"sort":0,"content_type":1,"score":2},{"id":38733,"content_id":52998,"sort":0,"content_type":1,"score":2},{"id":38734,"content_id":53003,"sort":0,"content_type":1,"score":2},{"id":38735,"content_id":53004,"sort":0,"content_type":1,"score":2},{"id":38736,"content_id":53006,"sort":0,"content_type":1,"score":2},{"id":38737,"content_id":53011,"sort":0,"content_type":1,"score":2},{"id":38738,"content_id":53012,"sort":0,"content_type":1,"score":2},{"id":38739,"content_id":53017,"sort":0,"content_type":1,"score":2},{"id":38740,"content_id":53018,"sort":0,"content_type":1,"score":3},{"id":38741,"content_id":53019,"sort":0,"content_type":1,"score":3},{"id":38742,"content_id":53020,"sort":0,"content_type":1,"score":3},{"id":38743,"content_id":53021,"sort":0,"content_type":1,"score":3},{"id":38744,"content_id":53022,"sort":0,"content_type":1,"score":3},{"id":38745,"content_id":53023,"sort":0,"content_type":1,"score":3},{"id":38746,"content_id":53024,"sort":0,"content_type":1,"score":3},{"id":38747,"content_id":53025,"sort":0,"content_type":1,"score":3},{"id":38748,"content_id":53026,"sort":0,"content_type":1,"score":3},{"id":38749,"content_id":53027,"sort":0,"content_type":1,"score":3},{"id":38750,"content_id":53028,"sort":0,"content_type":1,"score":3},{"id":38751,"content_id":53029,"sort":0,"content_type":1,"score":3},{"id":38752,"content_id":53030,"sort":0,"content_type":1,"score":3},{"id":38753,"content_id":53031,"sort":0,"content_type":1,"score":3},{"id":38754,"content_id":53032,"sort":0,"content_type":1,"score":3},{"id":38755,"content_id":53033,"sort":0,"content_type":1,"score":3},{"id":38756,"content_id":53034,"sort":0,"content_type":1,"score":3},{"id":38757,"content_id":53035,"sort":0,"content_type":1,"score":3},{"id":38758,"content_id":53036,"sort":0,"content_type":1,"score":3},{"id":38759,"content_id":53037,"sort":0,"content_type":1,"score":3},{"id":38760,"content_id":53498,"sort":0,"content_type":1,"score":3},{"id":38761,"content_id":53038,"sort":0,"content_type":1,"score":3},{"id":38762,"content_id":53039,"sort":0,"content_type":1,"score":3},{"id":38763,"content_id":53040,"sort":0,"content_type":1,"score":3}]}]},{"id":694,"stage_day":14,"title":"B7U2基础训练一","test_flag":0,"content":"","tasks":[{"id":1109,"task_name":"B7U2基础训练一","task_image":"jichuxunlian.png","task_type":6,"duration":0,"task_detail":[{"id":38797,"content_id":52981,"sort":0,"content_type":1,"score":3},{"id":38798,"content_id":52983,"sort":0,"content_type":1,"score":3},{"id":38799,"content_id":52984,"sort":0,"content_type":1,"score":3},{"id":38800,"content_id":52988,"sort":0,"content_type":1,"score":3},{"id":38801,"content_id":52991,"sort":0,"content_type":1,"score":3},{"id":38802,"content_id":52992,"sort":0,"content_type":1,"score":3},{"id":38803,"content_id":53058,"sort":0,"content_type":1,"score":3},{"id":38804,"content_id":53061,"sort":0,"content_type":1,"score":3},{"id":38805,"content_id":53063,"sort":0,"content_type":1,"score":3},{"id":38806,"content_id":53066,"sort":0,"content_type":1,"score":3},{"id":38807,"content_id":53067,"sort":0,"content_type":1,"score":3},{"id":38808,"content_id":53070,"sort":0,"content_type":1,"score":3},{"id":38809,"content_id":53074,"sort":0,"content_type":1,"score":3},{"id":38810,"content_id":53075,"sort":0,"content_type":1,"score":3},{"id":38811,"content_id":53078,"sort":0,"content_type":1,"score":4},{"id":38812,"content_id":53101,"sort":0,"content_type":1,"score":4},{"id":38813,"content_id":53105,"sort":0,"content_type":1,"score":4},{"id":38814,"content_id":53172,"sort":0,"content_type":1,"score":4},{"id":38815,"content_id":53177,"sort":0,"content_type":1,"score":4},{"id":38816,"content_id":53178,"sort":0,"content_type":1,"score":4},{"id":38817,"content_id":53179,"sort":0,"content_type":1,"score":4},{"id":38818,"content_id":53180,"sort":0,"content_type":1,"score":4},{"id":38819,"content_id":53181,"sort":0,"content_type":1,"score":4},{"id":38820,"content_id":53182,"sort":0,"content_type":1,"score":4},{"id":38821,"content_id":53183,"sort":0,"content_type":1,"score":6},{"id":38822,"content_id":53184,"sort":0,"content_type":1,"score":6},{"id":38823,"content_id":53185,"sort":0,"content_type":1,"score":6}]}]},{"id":695,"stage_day":15,"title":"B7U2基础训练二","test_flag":0,"content":"","tasks":[{"id":1110,"task_name":"B7U2基础训练二","task_image":"jichuxunlian.png","task_type":6,"duration":0,"task_detail":[{"id":38824,"content_id":53186,"sort":0,"content_type":1,"score":2},{"id":38825,"content_id":53187,"sort":0,"content_type":1,"score":2},{"id":38826,"content_id":53188,"sort":0,"content_type":1,"score":2},{"id":38827,"content_id":53189,"sort":0,"content_type":1,"score":2},{"id":38828,"content_id":53190,"sort":0,"content_type":1,"score":3},{"id":38829,"content_id":53191,"sort":0,"content_type":1,"score":3},{"id":38830,"content_id":53192,"sort":0,"content_type":1,"score":3},{"id":38831,"content_id":53193,"sort":0,"content_type":1,"score":3},{"id":38832,"content_id":53194,"sort":0,"content_type":1,"score":4},{"id":38833,"content_id":53195,"sort":0,"content_type":1,"score":4},{"id":38834,"content_id":53196,"sort":0,"content_type":1,"score":4},{"id":38835,"content_id":53197,"sort":0,"content_type":1,"score":4},{"id":38836,"content_id":53198,"sort":0,"content_type":1,"score":4},{"id":38837,"content_id":53199,"sort":0,"content_type":1,"score":4},{"id":38838,"content_id":53200,"sort":0,"content_type":1,"score":4},{"id":38839,"content_id":53201,"sort":0,"content_type":1,"score":4},{"id":38840,"content_id":53202,"sort":0,"content_type":1,"score":4},{"id":38841,"content_id":53203,"sort":0,"content_type":1,"score":4},{"id":38842,"content_id":53205,"sort":0,"content_type":1,"score":4},{"id":38843,"content_id":53206,"sort":0,"content_type":1,"score":4},{"id":38844,"content_id":53266,"sort":0,"content_type":1,"score":4},{"id":38845,"content_id":53268,"sort":0,"content_type":1,"score":7},{"id":38846,"content_id":53272,"sort":0,"content_type":1,"score":7},{"id":38847,"content_id":53273,"sort":0,"content_type":1,"score":7},{"id":38848,"content_id":53496,"sort":0,"content_type":1,"score":7}]}]},{"id":696,"stage_day":16,"title":"B7U2综合提高","test_flag":0,"content":"","tasks":[{"id":1111,"task_name":"B7U2综合提高","task_image":"jichuxunlian.png","task_type":6,"duration":0,"task_detail":[{"id":38872,"content_id":53278,"sort":0,"content_type":1,"score":2},{"id":38873,"content_id":53279,"sort":0,"content_type":1,"score":2},{"id":38874,"content_id":53281,"sort":0,"content_type":1,"score":2},{"id":38875,"content_id":53286,"sort":0,"content_type":1,"score":2},{"id":38876,"content_id":53290,"sort":0,"content_type":1,"score":2},{"id":38877,"content_id":53293,"sort":0,"content_type":1,"score":2},{"id":38878,"content_id":53296,"sort":0,"content_type":1,"score":2},{"id":38879,"content_id":53299,"sort":0,"content_type":1,"score":2},{"id":38880,"content_id":53307,"sort":0,"content_type":1,"score":3},{"id":38881,"content_id":53308,"sort":0,"content_type":1,"score":3},{"id":38882,"content_id":53309,"sort":0,"content_type":1,"score":3},{"id":38883,"content_id":53311,"sort":0,"content_type":1,"score":3},{"id":38884,"content_id":53312,"sort":0,"content_type":1,"score":3},{"id":38885,"content_id":53315,"sort":0,"content_type":1,"score":3},{"id":38886,"content_id":53316,"sort":0,"content_type":1,"score":3},{"id":38887,"content_id":53326,"sort":0,"content_type":1,"score":3},{"id":38888,"content_id":53327,"sort":0,"content_type":1,"score":3},{"id":38889,"content_id":53329,"sort":0,"content_type":1,"score":3},{"id":38890,"content_id":53330,"sort":0,"content_type":1,"score":3},{"id":38891,"content_id":53332,"sort":0,"content_type":1,"score":3},{"id":38892,"content_id":53333,"sort":0,"content_type":1,"score":3},{"id":38893,"content_id":53335,"sort":0,"content_type":1,"score":3},{"id":38894,"content_id":53337,"sort":0,"content_type":1,"score":3},{"id":38895,"content_id":53341,"sort":0,"content_type":1,"score":3},{"id":38896,"content_id":53343,"sort":0,"content_type":1,"score":3},{"id":38897,"content_id":53344,"sort":0,"content_type":1,"score":3},{"id":38898,"content_id":53346,"sort":0,"content_type":1,"score":3},{"id":38899,"content_id":53347,"sort":0,"content_type":1,"score":3},{"id":38900,"content_id":53348,"sort":0,"content_type":1,"score":3},{"id":38901,"content_id":53350,"sort":0,"content_type":1,"score":3},{"id":38902,"content_id":53357,"sort":0,"content_type":1,"score":3},{"id":38903,"content_id":53358,"sort":0,"content_type":1,"score":3},{"id":38904,"content_id":53359,"sort":0,"content_type":1,"score":3},{"id":38905,"content_id":53360,"sort":0,"content_type":1,"score":3},{"id":38906,"content_id":53361,"sort":0,"content_type":1,"score":3},{"id":38907,"content_id":53362,"sort":0,"content_type":1,"score":3}]}]},{"id":697,"stage_day":17,"title":"B7U3基础训练一","test_flag":0,"content":"","tasks":[{"id":1112,"task_name":"B7U3基础训练一","task_image":"jichuxunlian.png","task_type":6,"duration":0,"task_detail":[{"id":38946,"content_id":53041,"sort":0,"content_type":1,"score":2},{"id":38947,"content_id":53042,"sort":0,"content_type":1,"score":2},{"id":38948,"content_id":53043,"sort":0,"content_type":1,"score":2},{"id":38949,"content_id":53044,"sort":0,"content_type":1,"score":3},{"id":38950,"content_id":53045,"sort":0,"content_type":1,"score":3},{"id":38951,"content_id":53046,"sort":0,"content_type":1,"score":3},{"id":38952,"content_id":53048,"sort":0,"content_type":1,"score":4},{"id":38953,"content_id":53049,"sort":0,"content_type":1,"score":4},{"id":38954,"content_id":53497,"sort":0,"content_type":1,"score":8},{"id":38955,"content_id":53051,"sort":0,"content_type":1,"score":4},{"id":38956,"content_id":53052,"sort":0,"content_type":1,"score":4},{"id":38957,"content_id":53054,"sort":0,"content_type":1,"score":4},{"id":38958,"content_id":53055,"sort":0,"content_type":1,"score":4},{"id":38959,"content_id":53056,"sort":0,"content_type":1,"score":4},{"id":38960,"content_id":53057,"sort":0,"content_type":1,"score":4},{"id":38961,"content_id":53059,"sort":0,"content_type":1,"score":4},{"id":38962,"content_id":53060,"sort":0,"content_type":1,"score":4},{"id":38963,"content_id":53062,"sort":0,"content_type":1,"score":4},{"id":38964,"content_id":53064,"sort":0,"content_type":1,"score":5},{"id":38965,"content_id":53065,"sort":0,"content_type":1,"score":6},{"id":38966,"content_id":53090,"sort":0,"content_type":1,"score":6},{"id":38967,"content_id":53092,"sort":0,"content_type":1,"score":8},{"id":38968,"content_id":53093,"sort":0,"content_type":1,"score":8}]}]},{"id":698,"stage_day":18,"title":"B7U3基础训练二","test_flag":0,"content":"","tasks":[{"id":1113,"task_name":"B7U3基础训练二","task_image":"jichuxunlian.png","task_type":6,"duration":0,"task_detail":[{"id":38969,"content_id":53094,"sort":0,"content_type":1,"score":3},{"id":38970,"content_id":53095,"sort":0,"content_type":1,"score":3},{"id":38971,"content_id":53096,"sort":0,"content_type":1,"score":3},{"id":38972,"content_id":53097,"sort":0,"content_type":1,"score":3},{"id":38973,"content_id":53098,"sort":0,"content_type":1,"score":3},{"id":38974,"content_id":53099,"sort":0,"content_type":1,"score":3},{"id":38975,"content_id":53100,"sort":0,"content_type":1,"score":3},{"id":38976,"content_id":53102,"sort":0,"content_type":1,"score":3},{"id":38977,"content_id":53104,"sort":0,"content_type":1,"score":3},{"id":38978,"content_id":53106,"sort":0,"content_type":1,"score":3},{"id":38979,"content_id":53107,"sort":0,"content_type":1,"score":3},{"id":38980,"content_id":53109,"sort":0,"content_type":1,"score":3},{"id":38981,"content_id":53111,"sort":0,"content_type":1,"score":3},{"id":38982,"content_id":53113,"sort":0,"content_type":1,"score":3},{"id":38983,"content_id":53115,"sort":0,"content_type":1,"score":3},{"id":38984,"content_id":53117,"sort":0,"content_type":1,"score":3},{"id":38985,"content_id":53119,"sort":0,"content_type":1,"score":3},{"id":38986,"content_id":53121,"sort":0,"content_type":1,"score":3},{"id":38987,"content_id":53125,"sort":0,"content_type":1,"score":3},{"id":38988,"content_id":53127,"sort":0,"content_type":1,"score":3},{"id":38989,"content_id":53129,"sort":0,"content_type":1,"score":3},{"id":38990,"content_id":53131,"sort":0,"content_type":1,"score":3},{"id":38991,"content_id":53134,"sort":0,"content_type":1,"score":3},{"id":38992,"content_id":53135,"sort":0,"content_type":1,"score":3},{"id":38993,"content_id":53136,"sort":0,"content_type":1,"score":4},{"id":38994,"content_id":53138,"sort":0,"content_type":1,"score":4},{"id":38995,"content_id":53140,"sort":0,"content_type":1,"score":4},{"id":38996,"content_id":53142,"sort":0,"content_type":1,"score":4},{"id":38997,"content_id":53145,"sort":0,"content_type":1,"score":6},{"id":38998,"content_id":53148,"sort":0,"content_type":1,"score":6}]}]},{"id":699,"stage_day":19,"title":"B7U3综合提高","test_flag":0,"content":"","tasks":[{"id":1114,"task_name":"B7U3综合提高","task_image":"jichuxunlian.png","task_type":6,"duration":0,"task_detail":[{"id":38999,"content_id":53161,"sort":0,"content_type":1,"score":2},{"id":39000,"content_id":53162,"sort":0,"content_type":1,"score":2},{"id":39001,"content_id":53163,"sort":0,"content_type":1,"score":2},{"id":39002,"content_id":53164,"sort":0,"content_type":1,"score":2},{"id":39003,"content_id":53165,"sort":0,"content_type":1,"score":2},{"id":39004,"content_id":53166,"sort":0,"content_type":1,"score":2},{"id":39005,"content_id":53167,"sort":0,"content_type":1,"score":2},{"id":39006,"content_id":53168,"sort":0,"content_type":1,"score":2},{"id":39007,"content_id":53169,"sort":0,"content_type":1,"score":3},{"id":39008,"content_id":53170,"sort":0,"content_type":1,"score":3},{"id":39009,"content_id":53171,"sort":0,"content_type":1,"score":3},{"id":39010,"content_id":53173,"sort":0,"content_type":1,"score":3},{"id":39011,"content_id":53174,"sort":0,"content_type":1,"score":3},{"id":39012,"content_id":53175,"sort":0,"content_type":1,"score":3},{"id":39013,"content_id":53176,"sort":0,"content_type":1,"score":3},{"id":39014,"content_id":53214,"sort":0,"content_type":1,"score":3},{"id":39015,"content_id":53218,"sort":0,"content_type":1,"score":3},{"id":39016,"content_id":53221,"sort":0,"content_type":1,"score":3},{"id":39017,"content_id":53223,"sort":0,"content_type":1,"score":3},{"id":39018,"content_id":53226,"sort":0,"content_type":1,"score":3},{"id":39019,"content_id":53232,"sort":0,"content_type":1,"score":3},{"id":39020,"content_id":53234,"sort":0,"content_type":1,"score":3},{"id":39021,"content_id":53235,"sort":0,"content_type":1,"score":3},{"id":39022,"content_id":53238,"sort":0,"content_type":1,"score":3},{"id":39023,"content_id":53240,"sort":0,"content_type":1,"score":3},{"id":39024,"content_id":53242,"sort":0,"content_type":1,"score":3},{"id":39025,"content_id":53244,"sort":0,"content_type":1,"score":3},{"id":39026,"content_id":53246,"sort":0,"content_type":1,"score":3},{"id":39041,"content_id":53249,"sort":0,"content_type":1,"score":4},{"id":39042,"content_id":53251,"sort":0,"content_type":1,"score":4},{"id":39043,"content_id":53254,"sort":0,"content_type":1,"score":4},{"id":39044,"content_id":53257,"sort":0,"content_type":1,"score":4},{"id":39045,"content_id":53258,"sort":0,"content_type":1,"score":4},{"id":39046,"content_id":53260,"sort":0,"content_type":1,"score":4}]}]}]}],"course_name":"高二词汇进阶人教版","days":19,"course_group":"1","source":"/courserelease/37.zip"},"description":"success","result_code":200}