{"data":{"course_id":74,"stage":[{"id":108,"stage_name":"第一阶段","stage_image":"","stage_path":"","stage_mask_image":"","days":[{"id":1062,"stage_day":1,"title":"听力试题41","test_flag":0,"content":"","tasks":[{"id":1512,"task_name":"听力试题41","task_image":"jichuxunlian.png","task_type":6,"duration":0,"task_detail":[{"id":47673,"content_id":61251,"sort":0,"content_type":1,"score":4},{"id":47674,"content_id":61252,"sort":0,"content_type":1,"score":4},{"id":47675,"content_id":61253,"sort":0,"content_type":1,"score":4},{"id":47676,"content_id":61254,"sort":0,"content_type":1,"score":4},{"id":47677,"content_id":61255,"sort":0,"content_type":1,"score":4},{"id":47678,"content_id":61256,"sort":0,"content_type":1,"score":8},{"id":47679,"content_id":61260,"sort":0,"content_type":1,"score":8},{"id":47680,"content_id":61263,"sort":0,"content_type":1,"score":12},{"id":47681,"content_id":61265,"sort":0,"content_type":1,"score":16},{"id":47682,"content_id":61266,"sort":0,"content_type":1,"score":16},{"id":47683,"content_id":61281,"sort":0,"content_type":1,"score":4},{"id":47684,"content_id":61282,"sort":0,"content_type":1,"score":4},{"id":47685,"content_id":61283,"sort":0,"content_type":1,"score":4},{"id":47686,"content_id":61284,"sort":0,"content_type":1,"score":4},{"id":47687,"content_id":61285,"sort":0,"content_type":1,"score":4}]}]},{"id":1063,"stage_day":2,"title":"听力试题42","test_flag":0,"content":"","tasks":[{"id":1513,"task_name":"听力试题42","task_image":"jichuxunlian.png","task_type":6,"duration":0,"task_detail":[{"id":47688,"content_id":61313,"sort":0,"content_type":1,"score":4},{"id":47689,"content_id":61315,"sort":0,"content_type":1,"score":4},{"id":47690,"content_id":61316,"sort":0,"content_type":1,"score":4},{"id":47691,"content_id":61317,"sort":0,"content_type":1,"score":4},{"id":47692,"content_id":61318,"sort":0,"content_type":1,"score":4},{"id":47693,"content_id":61321,"sort":0,"content_type":1,"score":8},{"id":47694,"content_id":61323,"sort":0,"content_type":1,"score":8},{"id":47695,"content_id":61325,"sort":0,"content_type":1,"score":12},{"id":47696,"content_id":61327,"sort":0,"content_type":1,"score":16},{"id":47697,"content_id":61328,"sort":0,"content_type":1,"score":16},{"id":47698,"content_id":61332,"sort":0,"content_type":1,"score":4},{"id":47699,"content_id":61333,"sort":0,"content_type":1,"score":4},{"id":47700,"content_id":61335,"sort":0,"content_type":1,"score":4},{"id":47701,"content_id":61336,"sort":0,"content_type":1,"score":4},{"id":47702,"content_id":61337,"sort":0,"content_type":1,"score":4}]}]},{"id":1064,"stage_day":3,"title":"听力试题43","test_flag":0,"content":"","tasks":[{"id":1514,"task_name":"听力试题43","task_image":"jichuxunlian.png","task_type":6,"duration":0,"task_detail":[{"id":47703,"content_id":61343,"sort":0,"content_type":1,"score":4},{"id":47704,"content_id":61344,"sort":0,"content_type":1,"score":4},{"id":47705,"content_id":61346,"sort":0,"content_type":1,"score":4},{"id":47706,"content_id":61347,"sort":0,"content_type":1,"score":4},{"id":47707,"content_id":61348,"sort":0,"content_type":1,"score":4},{"id":47708,"content_id":61351,"sort":0,"content_type":1,"score":8},{"id":47709,"content_id":61353,"sort":0,"content_type":1,"score":8},{"id":47710,"content_id":61355,"sort":0,"content_type":1,"score":12},{"id":47711,"content_id":61357,"sort":0,"content_type":1,"score":16},{"id":47712,"content_id":61359,"sort":0,"content_type":1,"score":16},{"id":47713,"content_id":61360,"sort":0,"content_type":1,"score":4},{"id":47714,"content_id":61361,"sort":0,"content_type":1,"score":4},{"id":47715,"content_id":61363,"sort":0,"content_type":1,"score":4},{"id":47716,"content_id":61364,"sort":0,"content_type":1,"score":4},{"id":47717,"content_id":61365,"sort":0,"content_type":1,"score":4}]}]},{"id":1065,"stage_day":4,"title":"听力试题44","test_flag":0,"content":"","tasks":[{"id":1515,"task_name":"听力试题44","task_image":"jichuxunlian.png","task_type":6,"duration":0,"task_detail":[{"id":47718,"content_id":61367,"sort":0,"content_type":1,"score":4},{"id":47719,"content_id":61368,"sort":0,"content_type":1,"score":4},{"id":47720,"content_id":61369,"sort":0,"content_type":1,"score":4},{"id":47721,"content_id":61374,"sort":0,"content_type":1,"score":4},{"id":47722,"content_id":61375,"sort":0,"content_type":1,"score":4},{"id":47723,"content_id":61378,"sort":0,"content_type":1,"score":8},{"id":47724,"content_id":61379,"sort":0,"content_type":1,"score":8},{"id":47725,"content_id":61381,"sort":0,"content_type":1,"score":12},{"id":47726,"content_id":61389,"sort":0,"content_type":1,"score":16},{"id":47727,"content_id":61391,"sort":0,"content_type":1,"score":16},{"id":47728,"content_id":61393,"sort":0,"content_type":1,"score":4},{"id":47729,"content_id":61394,"sort":0,"content_type":1,"score":4},{"id":47730,"content_id":61397,"sort":0,"content_type":1,"score":4},{"id":47731,"content_id":61399,"sort":0,"content_type":1,"score":4},{"id":47732,"content_id":61400,"sort":0,"content_type":1,"score":4}]}]},{"id":1066,"stage_day":5,"title":"听力试题45","test_flag":0,"content":"","tasks":[{"id":1516,"task_name":"听力试题45","task_image":"jichuxunlian.png","task_type":6,"duration":0,"task_detail":[{"id":47733,"content_id":61407,"sort":0,"content_type":1,"score":4},{"id":47734,"content_id":61409,"sort":0,"content_type":1,"score":4},{"id":47735,"content_id":61410,"sort":0,"content_type":1,"score":4},{"id":47736,"content_id":61412,"sort":0,"content_type":1,"score":4},{"id":47737,"content_id":61413,"sort":0,"content_type":1,"score":4},{"id":47738,"content_id":61414,"sort":0,"content_type":1,"score":8},{"id":47739,"content_id":61416,"sort":0,"content_type":1,"score":8},{"id":47740,"content_id":61417,"sort":0,"content_type":1,"score":12},{"id":47741,"content_id":61419,"sort":0,"content_type":1,"score":16},{"id":47742,"content_id":61422,"sort":0,"content_type":1,"score":16},{"id":47743,"content_id":61425,"sort":0,"content_type":1,"score":2},{"id":47744,"content_id":61427,"sort":0,"content_type":1,"score":2},{"id":47745,"content_id":61429,"sort":0,"content_type":1,"score":4},{"id":47746,"content_id":61430,"sort":0,"content_type":1,"score":4},{"id":47747,"content_id":61431,"sort":0,"content_type":1,"score":4},{"id":47748,"content_id":61432,"sort":0,"content_type":1,"score":4}]}]},{"id":1067,"stage_day":6,"title":"听力试题46","test_flag":0,"content":"","tasks":[{"id":1517,"task_name":"听力试题46","task_image":"jichuxunlian.png","task_type":6,"duration":0,"task_detail":[{"id":47749,"content_id":61434,"sort":0,"content_type":1,"score":4},{"id":47750,"content_id":61436,"sort":0,"content_type":1,"score":4},{"id":47751,"content_id":61438,"sort":0,"content_type":1,"score":4},{"id":47752,"content_id":61439,"sort":0,"content_type":1,"score":4},{"id":47753,"content_id":61441,"sort":0,"content_type":1,"score":8},{"id":47754,"content_id":61443,"sort":0,"content_type":1,"score":8},{"id":47755,"content_id":61445,"sort":0,"content_type":1,"score":12},{"id":47756,"content_id":61447,"sort":0,"content_type":1,"score":16},{"id":47757,"content_id":61449,"sort":0,"content_type":1,"score":16},{"id":47758,"content_id":61451,"sort":0,"content_type":1,"score":4},{"id":47759,"content_id":61452,"sort":0,"content_type":1,"score":4},{"id":47760,"content_id":61453,"sort":0,"content_type":1,"score":4},{"id":47761,"content_id":61455,"sort":0,"content_type":1,"score":4},{"id":47762,"content_id":61456,"sort":0,"content_type":1,"score":4},{"id":47763,"content_id":61457,"sort":0,"content_type":1,"score":4}]}]},{"id":1068,"stage_day":7,"title":"听力试题47","test_flag":0,"content":"","tasks":[{"id":1518,"task_name":"听力试题47","task_image":"jichuxunlian.png","task_type":6,"duration":0,"task_detail":[{"id":47764,"content_id":61464,"sort":0,"content_type":1,"score":4},{"id":47765,"content_id":61466,"sort":0,"content_type":1,"score":4},{"id":47766,"content_id":61468,"sort":0,"content_type":1,"score":4},{"id":47767,"content_id":61470,"sort":0,"content_type":1,"score":4},{"id":47768,"content_id":61473,"sort":0,"content_type":1,"score":4},{"id":47769,"content_id":61475,"sort":0,"content_type":1,"score":8},{"id":47770,"content_id":61476,"sort":0,"content_type":1,"score":8},{"id":47771,"content_id":61478,"sort":0,"content_type":1,"score":12},{"id":47772,"content_id":61480,"sort":0,"content_type":1,"score":16},{"id":47773,"content_id":61482,"sort":0,"content_type":1,"score":16},{"id":47774,"content_id":61485,"sort":0,"content_type":1,"score":4},{"id":47775,"content_id":61486,"sort":0,"content_type":1,"score":4},{"id":47776,"content_id":61487,"sort":0,"content_type":1,"score":4},{"id":47777,"content_id":61489,"sort":0,"content_type":1,"score":4},{"id":47778,"content_id":61490,"sort":0,"content_type":1,"score":4}]}]},{"id":1069,"stage_day":8,"title":"听力试题48","test_flag":0,"content":"","tasks":[{"id":1519,"task_name":"听力试题48","task_image":"jichuxunlian.png","task_type":6,"duration":0,"task_detail":[{"id":47779,"content_id":61492,"sort":0,"content_type":1,"score":4},{"id":47780,"content_id":61494,"sort":0,"content_type":1,"score":4},{"id":47781,"content_id":61496,"sort":0,"content_type":1,"score":4},{"id":47782,"content_id":61498,"sort":0,"content_type":1,"score":4},{"id":47783,"content_id":61499,"sort":0,"content_type":1,"score":4},{"id":47784,"content_id":61502,"sort":0,"content_type":1,"score":8},{"id":47785,"content_id":61504,"sort":0,"content_type":1,"score":8},{"id":47786,"content_id":61506,"sort":0,"content_type":1,"score":12},{"id":47787,"content_id":61509,"sort":0,"content_type":1,"score":16},{"id":47788,"content_id":61512,"sort":0,"content_type":1,"score":16},{"id":47789,"content_id":61514,"sort":0,"content_type":1,"score":4},{"id":47790,"content_id":61515,"sort":0,"content_type":1,"score":4},{"id":47791,"content_id":61518,"sort":0,"content_type":1,"score":4},{"id":47792,"content_id":61519,"sort":0,"content_type":1,"score":4},{"id":47793,"content_id":61520,"sort":0,"content_type":1,"score":4}]}]},{"id":1070,"stage_day":9,"title":"听力试题49","test_flag":0,"content":"","tasks":[{"id":1520,"task_name":"听力试题49","task_image":"jichuxunlian.png","task_type":6,"duration":0,"task_detail":[{"id":47794,"content_id":61544,"sort":0,"content_type":1,"score":4},{"id":47795,"content_id":61545,"sort":0,"content_type":1,"score":4},{"id":47796,"content_id":61546,"sort":0,"content_type":1,"score":4},{"id":47797,"content_id":61547,"sort":0,"content_type":1,"score":4},{"id":47798,"content_id":61548,"sort":0,"content_type":1,"score":4},{"id":47799,"content_id":61549,"sort":0,"content_type":1,"score":8},{"id":47800,"content_id":61550,"sort":0,"content_type":1,"score":8},{"id":47801,"content_id":61551,"sort":0,"content_type":1,"score":12},{"id":47802,"content_id":61552,"sort":0,"content_type":1,"score":16},{"id":47803,"content_id":61553,"sort":0,"content_type":1,"score":16},{"id":47804,"content_id":61554,"sort":0,"content_type":1,"score":4},{"id":47805,"content_id":61555,"sort":0,"content_type":1,"score":4},{"id":47806,"content_id":61556,"sort":0,"content_type":1,"score":4},{"id":47807,"content_id":61557,"sort":0,"content_type":1,"score":4},{"id":47808,"content_id":61558,"sort":0,"content_type":1,"score":4}]}]},{"id":1071,"stage_day":10,"title":"听力试题50","test_flag":0,"content":"","tasks":[{"id":1521,"task_name":"听力试题50","task_image":"jichuxunlian.png","task_type":6,"duration":0,"task_detail":[{"id":47809,"content_id":61559,"sort":0,"content_type":1,"score":4},{"id":47810,"content_id":61560,"sort":0,"content_type":1,"score":4},{"id":47811,"content_id":61561,"sort":0,"content_type":1,"score":4},{"id":47812,"content_id":61562,"sort":0,"content_type":1,"score":4},{"id":47813,"content_id":61563,"sort":0,"content_type":1,"score":4},{"id":47814,"content_id":61564,"sort":0,"content_type":1,"score":8},{"id":47815,"content_id":61565,"sort":0,"content_type":1,"score":8},{"id":47816,"content_id":61566,"sort":0,"content_type":1,"score":12},{"id":47817,"content_id":61567,"sort":0,"content_type":1,"score":16},{"id":47818,"content_id":61568,"sort":0,"content_type":1,"score":16},{"id":47819,"content_id":61569,"sort":0,"content_type":1,"score":2},{"id":47820,"content_id":61570,"sort":0,"content_type":1,"score":2},{"id":47821,"content_id":61571,"sort":0,"content_type":1,"score":4},{"id":47822,"content_id":61572,"sort":0,"content_type":1,"score":4},{"id":47823,"content_id":61573,"sort":0,"content_type":1,"score":4},{"id":47824,"content_id":61574,"sort":0,"content_type":1,"score":4}]}]}]}],"course_name":"高一听力五期","days":10,"course_group":"1","source":"/courserelease/74.zip"},"description":"success","result_code":200}